RWTHColors/__init__.py
RWTHColors/cm.py
RWTHColors/colors/__init__.py
RWTHColors/colors/colors.py
RWTHColors/mpl-styles/rwth-dark.mplstyle
RWTHColors/mpl-styles/rwth-full.mplstyle
RWTHColors/mpl-styles/rwth.mplstyle
rwthcolors-0.2.9.dist-info/METADATA
rwthcolors-0.2.9.dist-info/WHEEL
rwthcolors-0.2.9.dist-info/RECORD
